compas_cem/__init__.py
compas_cem/data/__init__.py
compas_cem/data/data.py
compas_cem/diagrams/__init__.py
compas_cem/diagrams/diagram.py
compas_cem/diagrams/form.py
compas_cem/diagrams/mixins/__init__.py
compas_cem/diagrams/mixins/edge_mixins.py
compas_cem/diagrams/mixins/node_mixins.py
compas_cem/diagrams/topology/__init__.py
compas_cem/diagrams/topology/mesh_mixins.py
compas_cem/diagrams/topology/topology.py
compas_cem/elements/__init__.py
compas_cem/elements/deviation.py
compas_cem/elements/edge.py
compas_cem/elements/node.py
compas_cem/elements/trail.py
compas_cem/equilibrium/__init__.py
compas_cem/equilibrium/force.py
compas_cem/equilibrium/force_numpy.py
compas_cem/ghpython/__init__.py
compas_cem/ghpython/artists.py
compas_cem/ghpython/install.py
compas_cem/ghpython/register.py
compas_cem/ghpython/uninstall.py
compas_cem/ghpython/components/CompasCem_ArtistColors/code.py
compas_cem/ghpython/components/CompasCem_ArtistColors/icon.png
compas_cem/ghpython/components/CompasCem_ArtistColors/metadata.json
compas_cem/ghpython/components/CompasCem_ArtistForm/code.py
compas_cem/ghpython/components/CompasCem_ArtistForm/icon.png
compas_cem/ghpython/components/CompasCem_ArtistForm/metadata.json
compas_cem/ghpython/components/CompasCem_ArtistTopology/code.py
compas_cem/ghpython/components/CompasCem_ArtistTopology/icon.png
compas_cem/ghpython/components/CompasCem_ArtistTopology/metadata.json
compas_cem/ghpython/components/CompasCem_ConstrainedFormFinding/code.py
compas_cem/ghpython/components/CompasCem_ConstrainedFormFinding/icon.png
compas_cem/ghpython/components/CompasCem_ConstrainedFormFinding/metadata.json
compas_cem/ghpython/components/CompasCem_ConstraintDeviationEdgeLength/code.py
compas_cem/ghpython/components/CompasCem_ConstraintDeviationEdgeLength/icon.png
compas_cem/ghpython/components/CompasCem_ConstraintDeviationEdgeLength/metadata.json
compas_cem/ghpython/components/CompasCem_ConstraintEdgeDirection/code.py
compas_cem-0.8.6.dist-info/AUTHORS.rst
compas_cem-0.8.6.dist-info/LICENSE
compas_cem-0.8.6.dist-info/METADATA
compas_cem-0.8.6.dist-info/WHEEL
compas_cem-0.8.6.dist-info/top_level.txt
compas_cem-0.8.6.dist-info/RECORD
