Metadata-Version: 2.1
Name: compas-cem
Version: 0.8.6
Summary: The Combinatorial Equilibrium Modeling framework for COMPAS
Home-page: https://github.com/arpastrana/compas_cem
Author: Rafael Pastrana
Author-email: arpj@princeton.edu
License: MIT license
Classifier: Development Status :: 4 - Beta
Classifier: Intended Audience :: Developers
Classifier: Topic :: Scientific/Engineering
Classifier: License :: OSI Approved :: MIT License
Classifier: Operating System :: Unix
Classifier: Operating System :: POSIX
Classifier: Operating System :: Microsoft :: Windows
Classifier: Programming Language :: Python
Classifier: Programming Language :: Python :: 3
Classifier: Programming Language :: Python :: 3.8
Classifier: Programming Language :: Python :: 3.9
Classifier: Programming Language :: Python :: Implementation :: CPython
Requires-Python: >=3.8
License-File: LICENSE
License-File: AUTHORS.rst
Requires-Dist: numpy<2
Requires-Dist: compas==1.17.10
Requires-Dist: trimesh==3.20.0
Requires-Dist: autograd
Requires-Dist: nlopt>2.7
